{  
   "jenkins-info":{  
      "qa1":{  
         "_class":"hudson.model.FreeStyleProject",
         "name":"polymer-qa1.dev.gloo.us",
         "url":"https://jenkins.gloo.us/job/polymer-qa1.dev.gloo.us/",
         "color":"blue",
         "type":"qa"
      },
      "qa10":{  
         "_class":"hudson.model.FreeStyleProject",
         "name":"polymer-qa10.dev.gloo.us",
         "url":"https://jenkins.gloo.us/job/polymer-qa10.dev.gloo.us/",
         "color":"blue",
         "type":"qa"
      },
      "qa11":{  
         "_class":"hudson.model.FreeStyleProject",
         "name":"polymer-qa11.dev.gloo.us",
         "url":"https://jenkins.gloo.us/job/polymer-qa11.dev.gloo.us/",
         "color":"blue",
         "type":"qa"
      },
      "qa2":{  
         "_class":"hudson.model.FreeStyleProject",
         "name":"polymer-qa2.dev.gloo.us",
         "url":"https://jenkins.gloo.us/job/polymer-qa2.dev.gloo.us/",
         "color":"blue",
         "type":"qa"
      },
      "qa3":{  
         "_class":"hudson.model.FreeStyleProject",
         "name":"polymer-qa3.dev.gloo.us",
         "url":"https://jenkins.gloo.us/job/polymer-qa3.dev.gloo.us/",
         "color":"blue",
         "type":"qa"
      },
      "qa4":{  
         "_class":"hudson.model.FreeStyleProject",
         "name":"polymer-qa4.dev.gloo.us",
         "url":"https://jenkins.gloo.us/job/polymer-qa4.dev.gloo.us/",
         "color":"blue",
         "type":"qa"
      },
      "qa5":{  
         "_class":"hudson.model.FreeStyleProject",
         "name":"polymer-qa5.dev.gloo.us",
         "url":"https://jenkins.gloo.us/job/polymer-qa5.dev.gloo.us/",
         "color":"blue_anime",
         "type":"qa"
      },
      "qa6":{  
         "_class":"hudson.model.FreeStyleProject",
         "name":"polymer-qa6.dev.gloo.us",
         "url":"https://jenkins.gloo.us/job/polymer-qa6.dev.gloo.us/",
         "color":"blue_anime",
         "type":"qa"
      },
      "qa7":{  
         "_class":"hudson.model.FreeStyleProject",
         "name":"polymer-qa7.dev.gloo.us",
         "url":"https://jenkins.gloo.us/job/polymer-qa7.dev.gloo.us/",
         "color":"blue_anime",
         "type":"qa"
      },
      "qa8":{  
         "_class":"hudson.model.FreeStyleProject",
         "name":"polymer-qa8.dev.gloo.us",
         "url":"https://jenkins.gloo.us/job/polymer-qa8.dev.gloo.us/",
         "color":"blue_anime",
         "type":"qa"
      },
      "qa9":{  
         "_class":"hudson.model.FreeStyleProject",
         "name":"polymer-qa9.dev.gloo.us",
         "url":"https://jenkins.gloo.us/job/polymer-qa9.dev.gloo.us/",
         "color":"blue_anime",
         "type":"qa"
      },
      "restricted1":{  
         "_class":"hudson.model.FreeStyleProject",
         "name":"polymer-restricted1.dev.gloo.us",
         "url":"https://jenkins.gloo.us/job/polymer-restricted1.dev.gloo.us/",
         "color":"blue",
         "type":"re"
      },
      "restricted2":{  
         "_class":"hudson.model.FreeStyleProject",
         "name":"polymer-restricted2.dev.gloo.us",
         "url":"https://jenkins.gloo.us/job/polymer-restricted2.dev.gloo.us/",
         "color":"red",
         "type":"re"
      },
      "uitest1":{  
         "_class":"hudson.model.FreeStyleProject",
         "name":"polymer-uitest1.dev.gloo.us",
         "url":"https://jenkins.gloo.us/job/polymer-uitest1.dev.gloo.us/",
         "color":"blue",
         "type":"ui"
      },
      "uitest10":{  
         "_class":"hudson.model.FreeStyleProject",
         "name":"polymer-uitest10.dev.gloo.us",
         "url":"https://jenkins.gloo.us/job/polymer-uitest10.dev.gloo.us/",
         "color":"blue",
         "type":"ui"
      },
      "uitest11":{  
         "_class":"hudson.model.FreeStyleProject",
         "name":"polymer-uitest11.dev.gloo.us",
         "url":"https://jenkins.gloo.us/job/polymer-uitest11.dev.gloo.us/",
         "color":"blue",
         "type":"ui"
      },
      "uitest2":{  
         "_class":"hudson.model.FreeStyleProject",
         "name":"polymer-uitest2.dev.gloo.us",
         "url":"https://jenkins.gloo.us/job/polymer-uitest2.dev.gloo.us/",
         "color":"blue",
         "type":"ui"
      },
      "uitest3":{  
         "_class":"hudson.model.FreeStyleProject",
         "name":"polymer-uitest3.dev.gloo.us",
         "url":"https://jenkins.gloo.us/job/polymer-uitest3.dev.gloo.us/",
         "color":"blue",
         "type":"ui"
      },
      "uitest4":{  
         "_class":"hudson.model.FreeStyleProject",
         "name":"polymer-uitest4.dev.gloo.us",
         "url":"https://jenkins.gloo.us/job/polymer-uitest4.dev.gloo.us/",
         "color":"red",
         "type":"ui"
      },
      "uitest5":{  
         "_class":"hudson.model.FreeStyleProject",
         "name":"polymer-uitest5.dev.gloo.us",
         "url":"https://jenkins.gloo.us/job/polymer-uitest5.dev.gloo.us/",
         "color":"blue",
         "type":"ui"
      },
      "uitest6":{  
         "_class":"hudson.model.FreeStyleProject",
         "name":"polymer-uitest6.dev.gloo.us",
         "url":"https://jenkins.gloo.us/job/polymer-uitest6.dev.gloo.us/",
         "color":"blue",
         "type":"ui"
      },
      "uitest7":{  
         "_class":"hudson.model.FreeStyleProject",
         "name":"polymer-uitest7.dev.gloo.us",
         "url":"https://jenkins.gloo.us/job/polymer-uitest7.dev.gloo.us/",
         "color":"blue",
         "type":"ui"
      },
      "uitest8":{  
         "_class":"hudson.model.FreeStyleProject",
         "name":"polymer-uitest8.dev.gloo.us",
         "url":"https://jenkins.gloo.us/job/polymer-uitest8.dev.gloo.us/",
         "color":"blue",
         "type":"ui"
      },
      "uitest9":{  
         "_class":"hudson.model.FreeStyleProject",
         "name":"polymer-uitest9.dev.gloo.us",
         "url":"https://jenkins.gloo.us/job/polymer-uitest9.dev.gloo.us/",
         "color":"blue",
         "type":"ui"
      }
   }
}